Metadata-Version: 2.1
Name: kubegen
Version: 1.0.4
Summary: A package to generate k8s policy file
Home-page: https://github.com/razaqK/kubegen
Author: Razaq Kloc
Author-email: razaqkor@gmail.com
License: UNKNOWN
Platform: UNKNOWN
Classifier: Intended Audience :: Developers
Classifier: Programming Language :: Python :: 3.6
Classifier: License :: OSI Approved :: MIT License
Classifier: Operating System :: OS Independent
Requires-Python: >=3.6
